school_of_prompt/__init__.py
school_of_prompt/optimize.py
school_of_prompt/analysis/__init__.py
school_of_prompt/analysis/results_analyzer.py
school_of_prompt/core/__init__.py
school_of_prompt/core/config.py
school_of_prompt/core/simple_interfaces.py
school_of_prompt/data/__init__.py
school_of_prompt/data/auto_loader.py
school_of_prompt/data/registry.py
school_of_prompt/metrics/__init__.py
school_of_prompt/metrics/auto_metrics.py
school_of_prompt/models/__init__.py
school_of_prompt/models/auto_model.py
school_of_prompt/production/__init__.py
school_of_prompt/production/batch.py
school_of_prompt/production/cache.py
school_of_prompt/production/error_handling.py
school_of_prompt/tasks/__init__.py
school_of_prompt/tasks/auto_task.py
tests/__init__.py
tests/run_tests.py
tests/test_basic.py
tests/test_examples_live.py
tests/test_framework.py
school_of_prompt-0.4.5.dist-info/METADATA
school_of_prompt-0.4.5.dist-info/WHEEL
school_of_prompt-0.4.5.dist-info/top_level.txt
school_of_prompt-0.4.5.dist-info/RECORD
