Metadata-Version: 2.4
Name: school-of-prompt
Version: 0.4.5
Summary: 🎸 Rock your prompts! Enterprise-grade prompt optimization with statistical rigor and production features
Home-page: https://github.com/gpereyra/school-of-prompt
Author: Gustavo Pereyra
Author-email: gpereyra@users.noreply.github.com
Classifier: Development Status :: 4 - Beta
Classifier: Intended Audience :: Developers
Classifier: License :: OSI Approved :: MIT License
Classifier: Operating System :: OS Independent
Classifier: Programming Language :: Python :: 3
Classifier: Programming Language :: Python :: 3.8
Classifier: Programming Language :: Python :: 3.9
Classifier: Programming Language :: Python :: 3.10
Classifier: Programming Language :: Python :: 3.11
Classifier: Topic :: Scientific/Engineering :: Artificial Intelligence
Classifier: Topic :: Software Development :: Libraries :: Python Modules
Requires-Python: >=3.8
Requires-Dist: pandas>=1.3.0
Requires-Dist: openai>=1.0.0
Requires-Dist: PyYAML>=5.4.0
Provides-Extra: dev
Requires-Dist: pytest>=6.0; extra == "dev"
Requires-Dist: black>=21.0; extra == "dev"
Requires-Dist: flake8>=3.8; extra == "dev"
Provides-Extra: anthropic
Requires-Dist: anthropic>=0.3.0; extra == "anthropic"
Dynamic: author
Dynamic: author-email
Dynamic: classifier
Dynamic: description
Dynamic: description-content-type
Dynamic: home-page
Dynamic: provides-extra
Dynamic: requires-dist
Dynamic: requires-python
Dynamic: summary
